README
setup.py
r_norm/__init__.py
r_norm/parser.py
r_norm.egg-info/PKG-INFO
r_norm.egg-info/SOURCES.txt
r_norm.egg-info/dependency_links.txt
r_norm.egg-info/requires.txt
r_norm.egg-info/top_level.txt
tests/__init__.py