Metadata-Version: 1.0
Name: r-norm
Version: 0.1.0.1
Summary: Simple normalization of RTF files - removing unnesessary tagsthat can be produced by document processor program
Home-page: http://packages.python.org/r_norm
Author: Ruslan Khalikov
Author-email: khalikoff@gmail.com
License: Apache v2
Keywords: RTF
Platform: UNKNOWN
Classifier: Development Status :: 4 - Beta
Classifier: Intended Audience :: Developers
Classifier: Topic :: Utilities
Classifier: License :: OSI Approved :: Apache Software License
Classifier: Programming Language :: Python :: 2.6
Classifier: Programming Language :: Python :: 2.7
